odoo/addons/test_base_binary_url_import/README.rst
odoo/addons/test_base_binary_url_import/__init__.py
odoo/addons/test_base_binary_url_import/__manifest__.py
odoo/addons/test_base_binary_url_import/demo/demo_test_binary.xml
odoo/addons/test_base_binary_url_import/i18n/test_base_binary_url_import.pot
odoo/addons/test_base_binary_url_import/models/__init__.py
odoo/addons/test_base_binary_url_import/models/test_binary.py
odoo/addons/test_base_binary_url_import/readme/CONTRIBUTORS.rst
odoo/addons/test_base_binary_url_import/readme/DESCRIPTION.rst
odoo/addons/test_base_binary_url_import/security/ir.model.access.csv
odoo/addons/test_base_binary_url_import/static/description/icon.png
odoo/addons/test_base_binary_url_import/static/description/index.html
odoo/addons/test_base_binary_url_import/tests/__init__.py
odoo/addons/test_base_binary_url_import/tests/test_binary_import.py
odoo/addons/test_base_binary_url_import/tests/files/test.pdf
odoo/addons/test_base_binary_url_import/tests/files/test.txt
odoo/addons/test_base_binary_url_import/views/test_binary.xml
odoo13_addon_test_base_binary_url_import-13.0.1.0.1.dev4.dist-info/METADATA
odoo13_addon_test_base_binary_url_import-13.0.1.0.1.dev4.dist-info/WHEEL
odoo13_addon_test_base_binary_url_import-13.0.1.0.1.dev4.dist-info/top_level.txt
odoo13_addon_test_base_binary_url_import-13.0.1.0.1.dev4.dist-info/RECORD
